tsdat/__init__.py
tsdat/__main__.py
tsdat/_version.py
tsdat/py.typed
tsdat/testing.py
tsdat/cli/__init__.py
tsdat/cli/cli.py
tsdat/cli/generate_schema/__init__.py
tsdat/cli/generate_schema/generate_schema.py
tsdat/cli/generate_schema/vap_retriever_config.py
tsdat/config/__init__.py
tsdat/config/attributes/__init__.py
tsdat/config/attributes/acdd_global_attrs.py
tsdat/config/attributes/attribute_model.py
tsdat/config/attributes/global_attributes.py
tsdat/config/attributes/ioos_global_attrs.py
tsdat/config/dataset/__init__.py
tsdat/config/dataset/acdd_dataset_config.py
tsdat/config/dataset/dataset_config.py
tsdat/config/dataset/ioos_dataset_config.py
tsdat/config/pipeline/__init__.py
tsdat/config/pipeline/pipeline_config.py
tsdat/config/quality/__init__.py
tsdat/config/quality/checker_config.py
tsdat/config/quality/handler_config.py
tsdat/config/quality/manager_config.py
tsdat/config/quality/quality_config.py
tsdat/config/retriever/__init__.py
tsdat/config/retriever/data_converter_config.py
tsdat/config/retriever/data_reader_config.py
tsdat/config/retriever/retrieved_variable_config.py
tsdat/config/retriever/retriever_config.py
tsdat/config/storage/__init__.py
tsdat/config/storage/data_handler_config.py
tsdat/config/storage/storage_config.py
tsdat/config/utils/__init__.py
tsdat/config/utils/_named_class.py
tsdat/config/utils/config.py
tsdat/config/utils/config_error.py
tsdat/config/utils/find_duplicates.py
tsdat/config/utils/get_code_version.py
tsdat/config/utils/matches_overridable_schema.py
tsdat/config/utils/overrideable.py
tsdat/config/utils/parameterized_config_class.py
tsdat/config/utils/read_yaml.py
tsdat/config/utils/recursive_instantiate.py
tsdat/config/utils/yaml_model.py
tsdat/config/variables/__init__.py
tsdat/config/variables/coordinate.py
tsdat/config/variables/ureg.py
tsdat/config/variables/variable.py
tsdat/config/variables/variable_attributes.py
tsdat/const/__init__.py
tsdat/const/const.py
tsdat/io/__init__.py
tsdat/io/base/__init__.py
tsdat-0.9.0.dist-info/licenses/LICENSE.md
tsdat-0.9.0.dist-info/METADATA
tsdat-0.9.0.dist-info/WHEEL
tsdat-0.9.0.dist-info/entry_points.txt
tsdat-0.9.0.dist-info/top_level.txt
tsdat-0.9.0.dist-info/RECORD
