Metadata-Version: 2.4
Name: tsdat
Version: 0.9.0
Summary: A data processing framework used to convert time series data into standardized format.
Author-email: tsdat <tsdat@pnnl.gov>
License: **Time Series Data Utilities**
Keywords: data,pipeline
Classifier: Development Status :: 3 - Alpha
Classifier: Programming Language :: Python :: 3
Classifier: Topic :: Scientific/Engineering
Classifier: Intended Audience :: Science/Research
Requires-Python: >=3.10
License-File: LICENSE.md
Requires-Dist: act-atmos!=1.3.1,!=1.3.3,>=1.1.3
Requires-Dist: cftime
Requires-Dist: dunamai==1.9.0
Requires-Dist: jsonpointer==2.2
Requires-Dist: netCDF4
Requires-Dist: numpy<2.0
Requires-Dist: pandas>=1.2
Requires-Dist: pint
Requires-Dist: pydantic<2.0.0,>=1.10.0
Requires-Dist: pyyaml>=5.4
Requires-Dist: rich
Requires-Dist: typer>=0.4
Requires-Dist: xarray
Provides-Extra: aws
Requires-Dist: boto3; extra == "aws"
Provides-Extra: complete
Requires-Dist: tsdat[aws,io,ocean,transform]; extra == "complete"
Provides-Extra: dev
Requires-Dist: tsdat[complete]; extra == "dev"
Requires-Dist: black; extra == "dev"
Requires-Dist: boto3-stubs[essential]; extra == "dev"
Requires-Dist: build; extra == "dev"
Requires-Dist: coverage; extra == "dev"
Requires-Dist: mkdocs-gen-files; extra == "dev"
Requires-Dist: mkdocs-literate-nav; extra == "dev"
Requires-Dist: mkdocs-material; extra == "dev"
Requires-Dist: mkdocstrings[python]; extra == "dev"
Requires-Dist: moto[s3,sts]>5.1; extra == "dev"
Requires-Dist: mypy; extra == "dev"
Requires-Dist: pandas-stubs; extra == "dev"
Requires-Dist: pytest; extra == "dev"
Requires-Dist: ruff; extra == "dev"
Requires-Dist: types-PyYAML; extra == "dev"
Provides-Extra: io
Requires-Dist: h5netcdf; extra == "io"
Requires-Dist: pyarrow; extra == "io"
Requires-Dist: zarr; extra == "io"
Provides-Extra: ocean
Requires-Dist: mhkit; extra == "ocean"
Requires-Dist: matplotlib!=3.9.1.post1; extra == "ocean"
Provides-Extra: transform
Requires-Dist: numpy<2.0.0; extra == "transform"
Dynamic: license-file
